financialdatapy/__init__.py
financialdatapy/dartapi.py
financialdatapy/date.py
financialdatapy/exception.py
financialdatapy/filings.py
financialdatapy/financials.py
financialdatapy/market.py
financialdatapy/price.py
financialdatapy/request.py
financialdatapy/search.py
financialdatapy/stock.py
financialdatapy/stocklist.py
financialdatapy-1.2.2.dist-info/LICENSE
financialdatapy-1.2.2.dist-info/METADATA
financialdatapy-1.2.2.dist-info/WHEEL
financialdatapy-1.2.2.dist-info/top_level.txt
financialdatapy-1.2.2.dist-info/RECORD
