Metadata-Version: 2.1
Name: financialdatapy
Version: 1.2.2
Summary: Extract financial data of a company.
Home-page: UNKNOWN
Author: Choi Jiwoo
Author-email: cho2.jiwoo@gmail.com
License: MIT
Project-URL: Source, https://github.com/choi-jiwoo/financialdatapy
Keywords: python,stock,finance
Platform: UNKNOWN
Classifier: Development Status :: 3 - Alpha
Classifier: Intended Audience :: Education
Classifier: Programming Language :: Python :: 3.10
Classifier: License :: OSI Approved :: MIT License
Classifier: Operating System :: OS Independent
Requires-Python: >=3.10
License-File: LICENSE
Requires-Dist: pandas (>=1.4.0)
Requires-Dist: requests (>=2.27.1)
Requires-Dist: xmltodict (>=0.12.0)
Requires-Dist: python-dotenv (>=0.19.2)
Requires-Dist: beautifulsoup4 (>=4.10.0)
Requires-Dist: lxml (>=4.7.1)
Requires-Dist: user-agent (>=0.1.10)
